{
    "example_source": [
        "▁我还",
        "澄清",
        "了",
        "在该",
        "会议上",
        "提出的",
        "若干",
        "事项",
        "。"
    ],
    "example_target": [
        "<s>",
        "▁i",
        "▁was",
        "▁able",
        "▁to",
        "▁provide",
        "▁clarification",
        "▁on",
        "▁some",
        "▁of",
        "▁the",
        "▁matters",
        "▁which",
        "▁were",
        "▁raised",
        "▁at",
        "▁that",
        "▁meeting",
        ".",
        "</s>"
    ],
    "hypotheses": [
        {
            "hypothesis": [
                "▁i",
                "▁have",
                "▁also",
                "▁clarification",
                "ed",
                "▁on",
                "▁a",
                "▁number",
                "▁of",
                "▁matters",
                "▁that",
                "▁have",
                "▁been",
                "▁made",
                "."
            ],
            "score": -15.819527626037598
        },
        {
            "hypothesis": [
                "▁i",
                "▁have",
                "▁also",
                "▁clarification",
                "ed",
                "▁on",
                "▁a",
                "▁number",
                "▁of",
                "▁matters",
                "▁which",
                "▁have",
                "▁been",
                "▁made",
                "."
            ],
            "score": -15.913958549499512
        },
        {
            "hypothesis": [
                "▁i",
                "▁have",
                "▁also",
                "▁clarification",
                "ed",
                "▁on",
                "▁a",
                "▁number",
                "▁of",
                "▁matters",
                "▁which",
                "▁have",
                "▁been",
                "▁taken",
                "."
            ],
            "score": -16.077512741088867
        },
        {
            "hypothesis": [
                "▁i",
                "▁have",
                "▁also",
                "▁clarification",
                "ed",
                "▁on",
                "▁a",
                "▁number",
                "▁of",
                "▁matters",
                "▁that",
                "▁have",
                "▁been",
                "▁made",
                "▁in",
                "▁the",
                "▁conference",
                "."
            ],
            "score": -18.081344604492188
        },
        {
            "hypothesis": [
                "▁i",
                "▁have",
                "▁also",
                "▁clarification",
                "ed",
                "▁on",
                "▁a",
                "▁number",
                "▁of",
                "▁matters",
                "▁that",
                "▁have",
                "▁been",
                "▁made",
                "▁in",
                "▁the",
                "▁meeting",
                "."
            ],
            "score": -18.19114875793457
        },
        {
            "hypothesis": [
                "▁i",
                "▁have",
                "▁also",
                "▁clarification",
                "ed",
                "▁on",
                "▁a",
                "▁number",
                "▁of",
                "▁matters",
                "▁which",
                "▁have",
                "▁been",
                "▁made",
                "▁in",
                "▁the",
                "▁conference",
                "."
            ],
            "score": -18.209440231323242
        },
        {
            "hypothesis": [
                "▁i",
                "▁have",
                "▁also",
                "▁clarification",
                "ed",
                "▁on",
                "▁a",
                "▁number",
                "▁of",
                "▁matters",
                "▁which",
                "▁have",
                "▁been",
                "▁made",
                "▁in",
                "▁the",
                "▁meeting",
                "."
            ],
            "score": -18.352216720581055
        },
        {
            "hypothesis": [
                "▁i",
                "▁have",
                "▁also",
                "▁clarification",
                "ed",
                "▁on",
                "▁a",
                "▁number",
                "▁of",
                "▁issues",
                "▁which",
                "▁have",
                "▁been",
                "▁made",
                "▁in",
                "▁the",
                "▁conference",
                "."
            ],
            "score": -18.438413619995117
        },
        {
            "hypothesis": [
                "▁i",
                "▁have",
                "▁also",
                "▁clarification",
                "ed",
                "▁on",
                "▁a",
                "▁number",
                "▁of",
                "▁matters",
                "▁that",
                "▁have",
                "▁been",
                "▁taken",
                "▁by",
                "▁the",
                "▁committee",
                "."
            ],
            "score": -18.664459228515625
        },
        {
            "hypothesis": [
                "▁i",
                "▁have",
                "▁also",
                "▁clarification",
                "ed",
                "▁on",
                "▁a",
                "▁number",
                "▁of",
                "▁matters",
                "▁which",
                "▁have",
                "▁been",
                "▁taken",
                "▁by",
                "▁the",
                "▁committee",
                "."
            ],
            "score": -18.686574935913086
        }
    ],
    "diagnostic_info": "eyJ0IjogIjIwMjUtMDMtMTZUMTQ6NTQ6MTIuNTQ5NjE3IiwgImgiOiAiSXZhbnMtTWFjQm9vay1BaXIubG9jYWwiLCAidSI6ICJyb290In0="
}